{
  "teamId": 1886,
  "teamName": "Rosengård",
  "matches": [
    {
      "matchId": 13292777,
      "date": "2025-08-22",
      "opponent": "Växjö DFF",
      "homeAway": "Home",
      "result": "LOOSE",
      "teamScore": 2,
      "oppScore": 3,
      "league": "Damallsvenskan",
      "players": [
        {
          "name": "Samantha Murphy",
          "goal": 0,
          "assist": 0,
          "minute": ""
        },
        {
          "name": "Emma Jansson",
          "goal": 1,
          "assist": 0,
          "minute": 69,
          "goalType": "regular"
        },
        {
          "name": "Halimatu Ayinde",
          "goal": 0,
          "assist": 0,
          "minute": ""
        },
        {
          "name": "Emma Pennsater",
          "goal": 1,
          "assist": 0,
          "minute": 60,
          "goalType": "regular"
        },
        {
          "name": "Thea Sørbo",
          "goal": 0,
          "assist": 0,
          "minute": ""
        },
        {
          "name": "Aemu Oyama",
          "goal": 0,
          "assist": 0,
          "minute": ""
        },
        {
          "name": "Emilia Pelgander",
          "goal": 0,
          "assist": 0,
          "minute": ""
        },
        {
          "name": "Molly Johansson",
          "goal": 0,
          "assist": 0,
          "minute": ""
        },
        {
          "name": "Anastasiya Pobegaylo",
          "goal": 0,
          "assist": 2,
          "minute": 69
        },
        {
          "name": "Anam Imo",
          "goal": 0,
          "assist": 0,
          "minute": ""
        },
        {
          "name": "Hanna Andersson",
          "goal": 0,
          "assist": 0,
          "minute": ""
        },
        {
          "name": "Elli Pikkujämsä",
          "goal": 0,
          "assist": 0,
          "minute": ""
        },
        {
          "name": "Emilia Larsson",
          "goal": 0,
          "assist": 0,
          "minute": ""
        },
        {
          "name": "Filippa Sjostrom",
          "goal": 0,
          "assist": 0,
          "minute": ""
        },
        {
          "name": "Shannon Lynn",
          "goal": 0,
          "assist": 0,
          "minute": ""
        },
        {
          "name": "Mikaela Stojanovska",
          "goal": 0,
          "assist": 0,
          "minute": ""
        },
        {
          "name": "Maja Johansson",
          "goal": 0,
          "assist": 0,
          "minute": ""
        },
        {
          "name": "Alice Enehov",
          "goal": 0,
          "assist": 0,
          "minute": ""
        },
        {
          "name": "Ísabella Tryggvadóttir",
          "goal": 0,
          "assist": 0,
          "minute": ""
        },
        {
          "name": "Tilde Bjorklund",
          "goal": 0,
          "assist": 0,
          "minute": ""
        }
      ]
    },
    {
      "matchId": 13292789,
      "date": "2025-08-16",
      "opponent": "Kristianstads DFF",
      "homeAway": "Away",
      "result": "LOOSE",
      "teamScore": 1,
      "oppScore": 2,
      "league": "Damallsvenskan",
      "players": [
        {
          "name": "Samantha Murphy",
          "goal": 0,
          "assist": 0,
          "minute": ""
        },
        {
          "name": "Emma Jansson",
          "goal": 0,
          "assist": 0,
          "minute": ""
        },
        {
          "name": "Halimatu Ayinde",
          "goal": 0,
          "assist": 0,
          "minute": ""
        },
        {
          "name": "Emma Pennsater",
          "goal": 1,
          "assist": 0,
          "minute": 56,
          "goalType": "regular"
        },
        {
          "name": "Molly Johansson",
          "goal": 0,
          "assist": 0,
          "minute": ""
        },
        {
          "name": "Aemu Oyama",
          "goal": 0,
          "assist": 0,
          "minute": ""
        },
        {
          "name": "Emilia Pelgander",
          "goal": 0,
          "assist": 0,
          "minute": ""
        },
        {
          "name": "Emilia Larsson",
          "goal": 0,
          "assist": 0,
          "minute": ""
        },
        {
          "name": "Hanna Andersson",
          "goal": 0,
          "assist": 0,
          "minute": ""
        },
        {
          "name": "Anastasiya Pobegaylo",
          "goal": 0,
          "assist": 0,
          "minute": ""
        },
        {
          "name": "Anam Imo",
          "goal": 0,
          "assist": 0,
          "minute": ""
        },
        {
          "name": "Ísabella Tryggvadóttir",
          "goal": 0,
          "assist": 0,
          "minute": ""
        },
        {
          "name": "Thea Sørbo",
          "goal": 0,
          "assist": 0,
          "minute": ""
        },
        {
          "name": "Alice Enehov",
          "goal": 0,
          "assist": 0,
          "minute": ""
        },
        {
          "name": "Filippa Sjostrom",
          "goal": 0,
          "assist": 0,
          "minute": ""
        },
        {
          "name": "Shannon Lynn",
          "goal": 0,
          "assist": 0,
          "minute": ""
        },
        {
          "name": "Mikaela Stojanovska",
          "goal": 0,
          "assist": 0,
          "minute": ""
        },
        {
          "name": "Jo-Anne Cronquist",
          "goal": 0,
          "assist": 0,
          "minute": ""
        },
        {
          "name": "Maja Johansson",
          "goal": 0,
          "assist": 0,
          "minute": ""
        },
        {
          "name": "Tilde Bjorklund",
          "goal": 0,
          "assist": 0,
          "minute": ""
        }
      ]
    },
    {
      "matchId": 13292796,
      "date": "2025-08-12",
      "opponent": "Hammarby IF",
      "homeAway": "Home",
      "result": "DRAW",
      "teamScore": 2,
      "oppScore": 2,
      "league": "Damallsvenskan",
      "players": [
        {
          "name": "Samantha Murphy",
          "goal": 0,
          "assist": 0,
          "minute": ""
        },
        {
          "name": "Thea Sørbo",
          "goal": 1,
          "assist": 0,
          "minute": 40,
          "goalType": "regular"
        },
        {
          "name": "Emma Jansson",
          "goal": 0,
          "assist": 0,
          "minute": ""
        },
        {
          "name": "Jo-Anne Cronquist",
          "goal": 0,
          "assist": 0,
          "minute": ""
        },
        {
          "name": "Elli Pikkujämsä",
          "goal": 0,
          "assist": 0,
          "minute": ""
        },
        {
          "name": "Molly Johansson",
          "goal": 0,
          "assist": 0,
          "minute": ""
        },
        {
          "name": "Anastasiya Pobegaylo",
          "goal": 0,
          "assist": 1,
          "minute": 29
        },
        {
          "name": "Aemu Oyama",
          "goal": 0,
          "assist": 0,
          "minute": ""
        },
        {
          "name": "Halimatu Ayinde",
          "goal": 0,
          "assist": 0,
          "minute": ""
        },
        {
          "name": "Hanna Andersson",
          "goal": 0,
          "assist": 1,
          "minute": 40
        },
        {
          "name": "Anam Imo",
          "goal": 1,
          "assist": 0,
          "minute": 29,
          "goalType": "regular"
        },
        {
          "name": "Emilia Larsson",
          "goal": 0,
          "assist": 0,
          "minute": ""
        },
        {
          "name": "Filippa Sjostrom",
          "goal": 0,
          "assist": 0,
          "minute": ""
        },
        {
          "name": "Emilia Pelgander",
          "goal": 0,
          "assist": 0,
          "minute": ""
        },
        {
          "name": "Saga Andersson",
          "goal": 0,
          "assist": 0,
          "minute": ""
        },
        {
          "name": "Emma Pennsater",
          "goal": 0,
          "assist": 0,
          "minute": ""
        },
        {
          "name": "Mikaela Stojanovska",
          "goal": 0,
          "assist": 0,
          "minute": ""
        },
        {
          "name": "Maja Johansson",
          "goal": 0,
          "assist": 0,
          "minute": ""
        },
        {
          "name": "Ísabella Tryggvadóttir",
          "goal": 0,
          "assist": 0,
          "minute": ""
        },
        {
          "name": "Oona Sevenius",
          "goal": 0,
          "assist": 0,
          "minute": ""
        }
      ]
    },
    {
      "matchId": 13292779,
      "date": "2025-08-08",
      "opponent": "Malmo FF",
      "homeAway": "Home",
      "result": "LOOSE",
      "teamScore": 0,
      "oppScore": 1,
      "league": "Damallsvenskan",
      "players": [
        {
          "name": "Samantha Murphy",
          "goal": 0,
          "assist": 0,
          "minute": ""
        },
        {
          "name": "Thea Sørbo",
          "goal": 0,
          "assist": 0,
          "minute": ""
        },
        {
          "name": "Emma Jansson",
          "goal": 0,
          "assist": 0,
          "minute": ""
        },
        {
          "name": "Jo-Anne Cronquist",
          "goal": 0,
          "assist": 0,
          "minute": ""
        },
        {
          "name": "Elli Pikkujämsä",
          "goal": 0,
          "assist": 0,
          "minute": ""
        },
        {
          "name": "Molly Johansson",
          "goal": 0,
          "assist": 0,
          "minute": ""
        },
        {
          "name": "Anastasiya Pobegaylo",
          "goal": 0,
          "assist": 0,
          "minute": ""
        },
        {
          "name": "Halimatu Ayinde",
          "goal": 0,
          "assist": 0,
          "minute": ""
        },
        {
          "name": "Emilia Pelgander",
          "goal": 0,
          "assist": 0,
          "minute": ""
        },
        {
          "name": "Oona Sevenius",
          "goal": 0,
          "assist": 0,
          "minute": ""
        },
        {
          "name": "Anam Imo",
          "goal": 0,
          "assist": 0,
          "minute": ""
        },
        {
          "name": "Hanna Andersson",
          "goal": 0,
          "assist": 0,
          "minute": ""
        },
        {
          "name": "Emilia Larsson",
          "goal": 0,
          "assist": 0,
          "minute": ""
        },
        {
          "name": "Aemu Oyama",
          "goal": 0,
          "assist": 0,
          "minute": ""
        },
        {
          "name": "Ísabella Tryggvadóttir",
          "goal": 0,
          "assist": 0,
          "minute": ""
        },
        {
          "name": "Maja Johansson",
          "goal": 0,
          "assist": 0,
          "minute": ""
        },
        {
          "name": "Saga Andersson",
          "goal": 0,
          "assist": 0,
          "minute": ""
        },
        {
          "name": "Emma Pennsater",
          "goal": 0,
          "assist": 0,
          "minute": ""
        },
        {
          "name": "Mikaela Stojanovska",
          "goal": 0,
          "assist": 0,
          "minute": ""
        },
        {
          "name": "Filippa Sjostrom",
          "goal": 0,
          "assist": 0,
          "minute": ""
        }
      ]
    },
    {
      "matchId": 14321169,
      "date": "2025-08-01",
      "opponent": "HB Køge",
      "homeAway": "Away",
      "result": "LOOSE",
      "teamScore": 0,
      "oppScore": 2,
      "league": "Women Club Friendly Games",
      "players": []
    },
    {
      "matchId": 14255919,
      "date": "2025-07-25",
      "opponent": "LSK Kvinner FK",
      "homeAway": "Home",
      "result": "WIN",
      "teamScore": 5,
      "oppScore": 2,
      "league": "Women Club Friendly Games",
      "players": []
    },
    {
      "matchId": 14216268,
      "date": "2025-07-18",
      "opponent": "FC Nordsjaelland",
      "homeAway": "Home",
      "result": "WIN",
      "teamScore": 1,
      "oppScore": 0,
      "league": "Women Club Friendly Games",
      "players": []
    },
    {
      "matchId": 13292770,
      "date": "2025-06-19",
      "opponent": "Vittsjö GIK",
      "homeAway": "Home",
      "result": "DRAW",
      "teamScore": 2,
      "oppScore": 2,
      "league": "Damallsvenskan",
      "players": [
        {
          "name": "Eartha Cumings",
          "goal": 0,
          "assist": 0,
          "minute": ""
        },
        {
          "name": "Emilie Woldvik",
          "goal": 0,
          "assist": 0,
          "minute": ""
        },
        {
          "name": "Jo-Anne Cronquist",
          "goal": 0,
          "assist": 0,
          "minute": ""
        },
        {
          "name": "Guðrún Arnardóttir",
          "goal": 0,
          "assist": 0,
          "minute": ""
        },
        {
          "name": "Anni Hartikainen",
          "goal": 0,
          "assist": 0,
          "minute": ""
        },
        {
          "name": "Emilia Pelgander",
          "goal": 0,
          "assist": 0,
          "minute": ""
        },
        {
          "name": "Halimatu Ayinde",
          "goal": 0,
          "assist": 0,
          "minute": ""
        },
        {
          "name": "Emilia Larsson",
          "goal": 1,
          "assist": 1,
          "minute": 69,
          "goalType": "regular"
        },
        {
          "name": "Emma Jansson",
          "goal": 1,
          "assist": 0,
          "minute": 25,
          "goalType": "regular"
        },
        {
          "name": "Molly Johansson",
          "goal": 0,
          "assist": 0,
          "minute": ""
        },
        {
          "name": "Oona Sevenius",
          "goal": 0,
          "assist": 0,
          "minute": ""
        },
        {
          "name": "Hanna Andersson",
          "goal": 0,
          "assist": 0,
          "minute": ""
        },
        {
          "name": "Bea Sprung",
          "goal": 0,
          "assist": 0,
          "minute": ""
        },
        {
          "name": "Ísabella Tryggvadóttir",
          "goal": 0,
          "assist": 0,
          "minute": ""
        },
        {
          "name": "Filippa Sjostrom",
          "goal": 0,
          "assist": 0,
          "minute": ""
        },
        {
          "name": "Shannon Lynn",
          "goal": 0,
          "assist": 0,
          "minute": ""
        },
        {
          "name": "Maja Johansson",
          "goal": 0,
          "assist": 0,
          "minute": ""
        },
        {
          "name": "Alice Enehov",
          "goal": 0,
          "assist": 0,
          "minute": ""
        },
        {
          "name": "Anna Lovisa Yng",
          "goal": 0,
          "assist": 0,
          "minute": ""
        }
      ]
    },
    {
      "matchId": 13292764,
      "date": "2025-06-14",
      "opponent": "Linköpings FC",
      "homeAway": "Away",
      "result": "WIN",
      "teamScore": 3,
      "oppScore": 0,
      "league": "Damallsvenskan",
      "players": [
        {
          "name": "Eartha Cumings",
          "goal": 0,
          "assist": 0,
          "minute": ""
        },
        {
          "name": "Emilie Woldvik",
          "goal": 1,
          "assist": 0,
          "minute": 66,
          "goalType": "regular"
        },
        {
          "name": "Jo-Anne Cronquist",
          "goal": 0,
          "assist": 0,
          "minute": ""
        },
        {
          "name": "Guðrún Arnardóttir",
          "goal": 0,
          "assist": 0,
          "minute": ""
        },
        {
          "name": "Anni Hartikainen",
          "goal": 0,
          "assist": 0,
          "minute": ""
        },
        {
          "name": "Bea Sprung",
          "goal": 0,
          "assist": 0,
          "minute": ""
        },
        {
          "name": "Emilia Pelgander",
          "goal": 0,
          "assist": 0,
          "minute": ""
        },
        {
          "name": "Emilia Larsson",
          "goal": 1,
          "assist": 0,
          "minute": 14,
          "goalType": "regular"
        },
        {
          "name": "Hanna Andersson",
          "goal": 0,
          "assist": 0,
          "minute": ""
        },
        {
          "name": "Ísabella Tryggvadóttir",
          "goal": 0,
          "assist": 0,
          "minute": ""
        },
        {
          "name": "Oona Sevenius",
          "goal": 1,
          "assist": 0,
          "minute": 60,
          "goalType": "regular"
        },
        {
          "name": "Molly Johansson",
          "goal": 0,
          "assist": 1,
          "minute": 60
        },
        {
          "name": "Maja Johansson",
          "goal": 0,
          "assist": 0,
          "minute": ""
        },
        {
          "name": "Filippa Sjostrom",
          "goal": 0,
          "assist": 0,
          "minute": ""
        },
        {
          "name": "Alice Enehov",
          "goal": 0,
          "assist": 0,
          "minute": ""
        },
        {
          "name": "Shannon Lynn",
          "goal": 0,
          "assist": 0,
          "minute": ""
        },
        {
          "name": "Halimatu Ayinde",
          "goal": 0,
          "assist": 0,
          "minute": ""
        }
      ]
    },
    {
      "matchId": 13292754,
      "date": "2025-06-07",
      "opponent": "AIK",
      "homeAway": "Away",
      "result": "LOOSE",
      "teamScore": 0,
      "oppScore": 1,
      "league": "Damallsvenskan",
      "players": [
        {
          "name": "Eartha Cumings",
          "goal": 0,
          "assist": 0,
          "minute": ""
        },
        {
          "name": "Emilie Woldvik",
          "goal": 0,
          "assist": 0,
          "minute": ""
        },
        {
          "name": "Emma Jansson",
          "goal": 0,
          "assist": 0,
          "minute": ""
        },
        {
          "name": "Guðrún Arnardóttir",
          "goal": 0,
          "assist": 0,
          "minute": ""
        },
        {
          "name": "Anni Hartikainen",
          "goal": 0,
          "assist": 0,
          "minute": ""
        },
        {
          "name": "Emilia Pelgander",
          "goal": 0,
          "assist": 0,
          "minute": ""
        },
        {
          "name": "Hanna Andersson",
          "goal": 0,
          "assist": 0,
          "minute": ""
        },
        {
          "name": "Emilia Larsson",
          "goal": 0,
          "assist": 0,
          "minute": ""
        },
        {
          "name": "Maja Johansson",
          "goal": 0,
          "assist": 0,
          "minute": ""
        },
        {
          "name": "Ísabella Tryggvadóttir",
          "goal": 0,
          "assist": 0,
          "minute": ""
        },
        {
          "name": "Oona Sevenius",
          "goal": 0,
          "assist": 0,
          "minute": ""
        },
        {
          "name": "Emma Pennsater",
          "goal": 0,
          "assist": 0,
          "minute": ""
        },
        {
          "name": "Jo-Anne Cronquist",
          "goal": 0,
          "assist": 0,
          "minute": ""
        },
        {
          "name": "Bea Sprung",
          "goal": 0,
          "assist": 0,
          "minute": ""
        },
        {
          "name": "Filippa Sjostrom",
          "goal": 0,
          "assist": 0,
          "minute": ""
        },
        {
          "name": "Alice Enehov",
          "goal": 0,
          "assist": 0,
          "minute": ""
        },
        {
          "name": "Saga Andersson",
          "goal": 0,
          "assist": 0,
          "minute": ""
        },
        {
          "name": "Rebecca Maravall Almqvist",
          "goal": 0,
          "assist": 0,
          "minute": ""
        }
      ]
    },
    {
      "matchId": 13292749,
      "date": "2025-05-24",
      "opponent": "BK Häcken FF",
      "homeAway": "Home",
      "result": "LOOSE",
      "teamScore": 0,
      "oppScore": 1,
      "league": "Damallsvenskan",
      "players": [
        {
          "name": "Eartha Cumings",
          "goal": 0,
          "assist": 0,
          "minute": ""
        },
        {
          "name": "Emilie Woldvik",
          "goal": 0,
          "assist": 0,
          "minute": ""
        },
        {
          "name": "Emma Jansson",
          "goal": 0,
          "assist": 0,
          "minute": ""
        },
        {
          "name": "Guðrún Arnardóttir",
          "goal": 0,
          "assist": 0,
          "minute": ""
        },
        {
          "name": "Molly Johansson",
          "goal": 0,
          "assist": 0,
          "minute": ""
        },
        {
          "name": "Halimatu Ayinde",
          "goal": 0,
          "assist": 0,
          "minute": ""
        },
        {
          "name": "Emilia Larsson",
          "goal": 0,
          "assist": 0,
          "minute": ""
        },
        {
          "name": "Jo-Anne Cronquist",
          "goal": 0,
          "assist": 0,
          "minute": ""
        },
        {
          "name": "Emilia Pelgander",
          "goal": 0,
          "assist": 0,
          "minute": ""
        },
        {
          "name": "Bea Sprung",
          "goal": 0,
          "assist": 0,
          "minute": ""
        },
        {
          "name": "Oona Sevenius",
          "goal": 0,
          "assist": 0,
          "minute": ""
        },
        {
          "name": "Hanna Andersson",
          "goal": 0,
          "assist": 0,
          "minute": ""
        },
        {
          "name": "Ísabella Tryggvadóttir",
          "goal": 0,
          "assist": 0,
          "minute": ""
        },
        {
          "name": "Maja Johansson",
          "goal": 0,
          "assist": 0,
          "minute": ""
        },
        {
          "name": "Tilde Bjorklund",
          "goal": 0,
          "assist": 0,
          "minute": ""
        },
        {
          "name": "Saga Andersson",
          "goal": 0,
          "assist": 0,
          "minute": ""
        },
        {
          "name": "Emma Pennsater",
          "goal": 0,
          "assist": 0,
          "minute": ""
        },
        {
          "name": "Anni Hartikainen",
          "goal": 0,
          "assist": 0,
          "minute": ""
        },
        {
          "name": "Alice Enehov",
          "goal": 0,
          "assist": 0,
          "minute": ""
        }
      ]
    },
    {
      "matchId": 13919115,
      "date": "2025-05-22",
      "opponent": "Ajax",
      "homeAway": "Home",
      "result": "LOOSE",
      "teamScore": 0,
      "oppScore": 2,
      "league": "W7F May Tournament, Group A",
      "players": [
        {
          "name": "Eartha Cumings",
          "goal": 0,
          "assist": 0,
          "minute": ""
        },
        {
          "name": "Guðrún Arnardóttir",
          "goal": 0,
          "assist": 0,
          "minute": ""
        },
        {
          "name": "Anni Hartikainen",
          "goal": 0,
          "assist": 0,
          "minute": ""
        },
        {
          "name": "Emma Jansson",
          "goal": 0,
          "assist": 0,
          "minute": ""
        },
        {
          "name": "Jo-Anne Cronquist",
          "goal": 0,
          "assist": 0,
          "minute": ""
        },
        {
          "name": "Oona Sevenius",
          "goal": 0,
          "assist": 0,
          "minute": ""
        },
        {
          "name": "Ísabella Tryggvadóttir",
          "goal": 0,
          "assist": 0,
          "minute": ""
        },
        {
          "name": "Saga Andersson",
          "goal": 0,
          "assist": 0,
          "minute": ""
        },
        {
          "name": "Halimatu Ayinde",
          "goal": 0,
          "assist": 0,
          "minute": ""
        },
        {
          "name": "Hanna Andersson",
          "goal": 0,
          "assist": 0,
          "minute": ""
        },
        {
          "name": "Molly Johansson",
          "goal": 0,
          "assist": 0,
          "minute": ""
        },
        {
          "name": "Maja Johansson",
          "goal": 0,
          "assist": 0,
          "minute": ""
        }
      ]
    },
    {
      "matchId": 13929724,
      "date": "2025-05-22",
      "opponent": "FC Bayern München",
      "homeAway": "Home",
      "result": "LOOSE",
      "teamScore": 0,
      "oppScore": 4,
      "league": "W7F May Tournament, Group A",
      "players": [
        {
          "name": "Eartha Cumings",
          "goal": 0,
          "assist": 0,
          "minute": ""
        },
        {
          "name": "Guðrún Arnardóttir",
          "goal": 0,
          "assist": 0,
          "minute": ""
        },
        {
          "name": "Emma Jansson",
          "goal": 0,
          "assist": 0,
          "minute": ""
        },
        {
          "name": "Jo-Anne Cronquist",
          "goal": 0,
          "assist": 0,
          "minute": ""
        },
        {
          "name": "Bea Sprung",
          "goal": 0,
          "assist": 0,
          "minute": ""
        },
        {
          "name": "Molly Johansson",
          "goal": 0,
          "assist": 0,
          "minute": ""
        },
        {
          "name": "Ísabella Tryggvadóttir",
          "goal": 0,
          "assist": 0,
          "minute": ""
        },
        {
          "name": "Saga Andersson",
          "goal": 0,
          "assist": 0,
          "minute": ""
        },
        {
          "name": "Emma Pennsater",
          "goal": 0,
          "assist": 0,
          "minute": ""
        },
        {
          "name": "Emilie Woldvik",
          "goal": 0,
          "assist": 0,
          "minute": ""
        },
        {
          "name": "Emilia Larsson",
          "goal": 0,
          "assist": 0,
          "minute": ""
        },
        {
          "name": "Hanna Andersson",
          "goal": 0,
          "assist": 0,
          "minute": ""
        },
        {
          "name": "Emilia Pelgander",
          "goal": 0,
          "assist": 0,
          "minute": ""
        },
        {
          "name": "Yuna Hazekawa",
          "goal": 0,
          "assist": 0,
          "minute": ""
        }
      ]
    },
    {
      "matchId": 13919034,
      "date": "2025-05-21",
      "opponent": "Manchester City",
      "homeAway": "Away",
      "result": "LOOSE",
      "teamScore": 0,
      "oppScore": 4,
      "league": "W7F May Tournament, Group A",
      "players": [
        {
          "name": "Eartha Cumings",
          "goal": 0,
          "assist": 0,
          "minute": ""
        },
        {
          "name": "Guðrún Arnardóttir",
          "goal": 0,
          "assist": 0,
          "minute": ""
        },
        {
          "name": "Emilie Woldvik",
          "goal": 0,
          "assist": 0,
          "minute": ""
        },
        {
          "name": "Anni Hartikainen",
          "goal": 0,
          "assist": 0,
          "minute": ""
        },
        {
          "name": "Emma Jansson",
          "goal": 0,
          "assist": 0,
          "minute": ""
        },
        {
          "name": "Emilia Larsson",
          "goal": 0,
          "assist": 0,
          "minute": ""
        },
        {
          "name": "Emilia Pelgander",
          "goal": 0,
          "assist": 0,
          "minute": ""
        },
        {
          "name": "Saga Andersson",
          "goal": 0,
          "assist": 0,
          "minute": ""
        },
        {
          "name": "Halimatu Ayinde",
          "goal": 0,
          "assist": 0,
          "minute": ""
        },
        {
          "name": "Jo-Anne Cronquist",
          "goal": 0,
          "assist": 0,
          "minute": ""
        },
        {
          "name": "Bea Sprung",
          "goal": 0,
          "assist": 0,
          "minute": ""
        },
        {
          "name": "Hanna Andersson",
          "goal": 0,
          "assist": 0,
          "minute": ""
        },
        {
          "name": "Maja Johansson",
          "goal": 0,
          "assist": 0,
          "minute": ""
        },
        {
          "name": "Oona Sevenius",
          "goal": 0,
          "assist": 0,
          "minute": ""
        }
      ]
    },
    {
      "matchId": 13292743,
      "date": "2025-05-17",
      "opponent": "IF Brommapojkarna",
      "homeAway": "Away",
      "result": "LOOSE",
      "teamScore": 1,
      "oppScore": 2,
      "league": "Damallsvenskan",
      "players": [
        {
          "name": "Eartha Cumings",
          "goal": 0,
          "assist": 0,
          "minute": ""
        },
        {
          "name": "Emilie Woldvik",
          "goal": 1,
          "assist": 0,
          "minute": 78,
          "goalType": "regular"
        },
        {
          "name": "Emma Jansson",
          "goal": 0,
          "assist": 0,
          "minute": ""
        },
        {
          "name": "Guðrún Arnardóttir",
          "goal": 0,
          "assist": 0,
          "minute": ""
        },
        {
          "name": "Jo-Anne Cronquist",
          "goal": 0,
          "assist": 0,
          "minute": ""
        },
        {
          "name": "Molly Johansson",
          "goal": 0,
          "assist": 0,
          "minute": ""
        },
        {
          "name": "Emilia Larsson",
          "goal": 0,
          "assist": 0,
          "minute": ""
        },
        {
          "name": "Bea Sprung",
          "goal": 0,
          "assist": 0,
          "minute": ""
        },
        {
          "name": "Halimatu Ayinde",
          "goal": 0,
          "assist": 0,
          "minute": ""
        },
        {
          "name": "Hanna Andersson",
          "goal": 0,
          "assist": 0,
          "minute": ""
        },
        {
          "name": "Oona Sevenius",
          "goal": 0,
          "assist": 0,
          "minute": ""
        },
        {
          "name": "Anni Hartikainen",
          "goal": 0,
          "assist": 0,
          "minute": ""
        },
        {
          "name": "Emilia Pelgander",
          "goal": 0,
          "assist": 0,
          "minute": ""
        },
        {
          "name": "Maja Johansson",
          "goal": 0,
          "assist": 0,
          "minute": ""
        },
        {
          "name": "Saga Andersson",
          "goal": 0,
          "assist": 0,
          "minute": ""
        },
        {
          "name": "Emma Pennsater",
          "goal": 0,
          "assist": 0,
          "minute": ""
        },
        {
          "name": "Alice Enehov",
          "goal": 0,
          "assist": 0,
          "minute": ""
        },
        {
          "name": "Yuna Hazekawa",
          "goal": 0,
          "assist": 0,
          "minute": ""
        },
        {
          "name": "Tilde Bjorklund",
          "goal": 0,
          "assist": 0,
          "minute": ""
        },
        {
          "name": "Anna Lovisa Yng",
          "goal": 0,
          "assist": 0,
          "minute": ""
        }
      ]
    },
    {
      "matchId": 13292735,
      "date": "2025-05-10",
      "opponent": "Norrköping DFK",
      "homeAway": "Home",
      "result": "WIN",
      "teamScore": 2,
      "oppScore": 1,
      "league": "Damallsvenskan",
      "players": [
        {
          "name": "Eartha Cumings",
          "goal": 0,
          "assist": 0,
          "minute": ""
        },
        {
          "name": "Emma Jansson",
          "goal": 0,
          "assist": 0,
          "minute": ""
        },
        {
          "name": "Guðrún Arnardóttir",
          "goal": 0,
          "assist": 0,
          "minute": ""
        },
        {
          "name": "Jo-Anne Cronquist",
          "goal": 0,
          "assist": 0,
          "minute": ""
        },
        {
          "name": "Emilie Woldvik",
          "goal": 0,
          "assist": 0,
          "minute": ""
        },
        {
          "name": "Halimatu Ayinde",
          "goal": 0,
          "assist": 0,
          "minute": ""
        },
        {
          "name": "Bea Sprung",
          "goal": 0,
          "assist": 0,
          "minute": ""
        },
        {
          "name": "Molly Johansson",
          "goal": 0,
          "assist": 0,
          "minute": ""
        },
        {
          "name": "Emilia Larsson",
          "goal": 1,
          "assist": 1,
          "minute": 74,
          "goalType": "regular"
        },
        {
          "name": "Hanna Andersson",
          "goal": 1,
          "assist": 0,
          "minute": 26,
          "goalType": "regular"
        },
        {
          "name": "Oona Sevenius",
          "goal": 0,
          "assist": 0,
          "minute": ""
        },
        {
          "name": "Maja Johansson",
          "goal": 0,
          "assist": 1,
          "minute": 74
        },
        {
          "name": "Anni Hartikainen",
          "goal": 0,
          "assist": 0,
          "minute": ""
        },
        {
          "name": "Emilia Pelgander",
          "goal": 0,
          "assist": 0,
          "minute": ""
        },
        {
          "name": "Saga Andersson",
          "goal": 0,
          "assist": 0,
          "minute": ""
        },
        {
          "name": "Emma Pennsater",
          "goal": 0,
          "assist": 0,
          "minute": ""
        },
        {
          "name": "Yuna Hazekawa",
          "goal": 0,
          "assist": 0,
          "minute": ""
        },
        {
          "name": "Filippa Sjostrom",
          "goal": 0,
          "assist": 0,
          "minute": ""
        }
      ]
    },
    {
      "matchId": 13292726,
      "date": "2025-05-04",
      "opponent": "Alingsås IF Fotboll",
      "homeAway": "Away",
      "result": "LOOSE",
      "teamScore": 0,
      "oppScore": 1,
      "league": "Damallsvenskan",
      "players": [
        {
          "name": "Eartha Cumings",
          "goal": 0,
          "assist": 0,
          "minute": ""
        },
        {
          "name": "Emma Jansson",
          "goal": 0,
          "assist": 0,
          "minute": ""
        },
        {
          "name": "Guðrún Arnardóttir",
          "goal": 0,
          "assist": 0,
          "minute": ""
        },
        {
          "name": "Jo-Anne Cronquist",
          "goal": 0,
          "assist": 0,
          "minute": ""
        },
        {
          "name": "Emilie Woldvik",
          "goal": 0,
          "assist": 0,
          "minute": ""
        },
        {
          "name": "Bea Sprung",
          "goal": 0,
          "assist": 0,
          "minute": ""
        },
        {
          "name": "Emilia Pelgander",
          "goal": 0,
          "assist": 0,
          "minute": ""
        },
        {
          "name": "Anni Hartikainen",
          "goal": 0,
          "assist": 0,
          "minute": ""
        },
        {
          "name": "Emilia Larsson",
          "goal": 0,
          "assist": 0,
          "minute": ""
        },
        {
          "name": "Oona Sevenius",
          "goal": 0,
          "assist": 0,
          "minute": ""
        },
        {
          "name": "Maja Johansson",
          "goal": 0,
          "assist": 0,
          "minute": ""
        },
        {
          "name": "Hanna Andersson",
          "goal": 0,
          "assist": 0,
          "minute": ""
        },
        {
          "name": "Molly Johansson",
          "goal": 0,
          "assist": 0,
          "minute": ""
        },
        {
          "name": "Halimatu Ayinde",
          "goal": 0,
          "assist": 0,
          "minute": ""
        },
        {
          "name": "Ísabella Tryggvadóttir",
          "goal": 0,
          "assist": 0,
          "minute": ""
        },
        {
          "name": "Shannon Lynn",
          "goal": 0,
          "assist": 0,
          "minute": ""
        },
        {
          "name": "Saga Andersson",
          "goal": 0,
          "assist": 0,
          "minute": ""
        },
        {
          "name": "Mikaela Stojanovska",
          "goal": 0,
          "assist": 0,
          "minute": ""
        },
        {
          "name": "Yuna Hazekawa",
          "goal": 0,
          "assist": 0,
          "minute": ""
        },
        {
          "name": "Filippa Sjostrom",
          "goal": 0,
          "assist": 0,
          "minute": ""
        }
      ]
    },
    {
      "matchId": 13676877,
      "date": "2025-05-01",
      "opponent": "Hammarby IF",
      "homeAway": "Away",
      "result": "LOOSE",
      "teamScore": 0,
      "oppScore": 5,
      "league": "Svenska Cupen, Women",
      "players": []
    },
    {
      "matchId": 13292721,
      "date": "2025-04-27",
      "opponent": "Djurgårdens IF DFF",
      "homeAway": "Away",
      "result": "DRAW",
      "teamScore": 2,
      "oppScore": 2,
      "league": "Damallsvenskan",
      "players": [
        {
          "name": "Eartha Cumings",
          "goal": 0,
          "assist": 0,
          "minute": ""
        },
        {
          "name": "Emilie Woldvik",
          "goal": 0,
          "assist": 0,
          "minute": ""
        },
        {
          "name": "Emma Pennsater",
          "goal": 0,
          "assist": 0,
          "minute": ""
        },
        {
          "name": "Guðrún Arnardóttir",
          "goal": 0,
          "assist": 0,
          "minute": ""
        },
        {
          "name": "Jo-Anne Cronquist",
          "goal": 0,
          "assist": 0,
          "minute": ""
        },
        {
          "name": "Bea Sprung",
          "goal": 0,
          "assist": 0,
          "minute": ""
        },
        {
          "name": "Emma Jansson",
          "goal": 0,
          "assist": 0,
          "minute": ""
        },
        {
          "name": "Emilia Pelgander",
          "goal": 0,
          "assist": 0,
          "minute": ""
        },
        {
          "name": "Molly Johansson",
          "goal": 1,
          "assist": 0,
          "minute": 34,
          "goalType": "regular"
        },
        {
          "name": "Oona Sevenius",
          "goal": 0,
          "assist": 0,
          "minute": ""
        },
        {
          "name": "Hanna Andersson",
          "goal": 1,
          "assist": 1,
          "minute": 34
        },
        {
          "name": "Maja Johansson",
          "goal": 0,
          "assist": 0,
          "minute": ""
        },
        {
          "name": "Anni Hartikainen",
          "goal": 0,
          "assist": 0,
          "minute": ""
        },
        {
          "name": "Emilia Larsson",
          "goal": 0,
          "assist": 0,
          "minute": ""
        },
        {
          "name": "Ísabella Tryggvadóttir",
          "goal": 0,
          "assist": 0,
          "minute": ""
        },
        {
          "name": "Saga Andersson",
          "goal": 0,
          "assist": 0,
          "minute": ""
        },
        {
          "name": "Mikaela Stojanovska",
          "goal": 0,
          "assist": 0,
          "minute": ""
        },
        {
          "name": "Yuna Hazekawa",
          "goal": 0,
          "assist": 0,
          "minute": ""
        },
        {
          "name": "Alice Enehov",
          "goal": 0,
          "assist": 0,
          "minute": ""
        }
      ]
    },
    {
      "matchId": 13292714,
      "date": "2025-04-21",
      "opponent": "Kristianstads DFF",
      "homeAway": "Home",
      "result": "WIN",
      "teamScore": 2,
      "oppScore": 1,
      "league": "Damallsvenskan",
      "players": [
        {
          "name": "Eartha Cumings",
          "goal": 0,
          "assist": 0,
          "minute": ""
        },
        {
          "name": "Emilie Woldvik",
          "goal": 0,
          "assist": 0,
          "minute": ""
        },
        {
          "name": "Emma Jansson",
          "goal": 0,
          "assist": 1,
          "minute": 48
        },
        {
          "name": "Guðrún Arnardóttir",
          "goal": 0,
          "assist": 0,
          "minute": ""
        },
        {
          "name": "Jo-Anne Cronquist",
          "goal": 0,
          "assist": 0,
          "minute": ""
        },
        {
          "name": "Molly Johansson",
          "goal": 0,
          "assist": 0,
          "minute": ""
        },
        {
          "name": "Bea Sprung",
          "goal": 1,
          "assist": 0,
          "minute": 26,
          "goalType": "regular"
        },
        {
          "name": "Emilia Pelgander",
          "goal": 0,
          "assist": 0,
          "minute": ""
        },
        {
          "name": "Halimatu Ayinde",
          "goal": 0,
          "assist": 0,
          "minute": ""
        },
        {
          "name": "Hanna Andersson",
          "goal": 0,
          "assist": 0,
          "minute": ""
        },
        {
          "name": "Oona Sevenius",
          "goal": 1,
          "assist": 0,
          "minute": 48,
          "goalType": "regular"
        },
        {
          "name": "Emilia Larsson",
          "goal": 0,
          "assist": 0,
          "minute": ""
        },
        {
          "name": "Anni Hartikainen",
          "goal": 0,
          "assist": 0,
          "minute": ""
        },
        {
          "name": "Saga Andersson",
          "goal": 0,
          "assist": 0,
          "minute": ""
        },
        {
          "name": "Mikaela Stojanovska",
          "goal": 0,
          "assist": 0,
          "minute": ""
        },
        {
          "name": "Emma Pennsater",
          "goal": 0,
          "assist": 0,
          "minute": ""
        },
        {
          "name": "Maja Johansson",
          "goal": 0,
          "assist": 0,
          "minute": ""
        },
        {
          "name": "Yuna Hazekawa",
          "goal": 0,
          "assist": 0,
          "minute": ""
        },
        {
          "name": "Ísabella Tryggvadóttir",
          "goal": 0,
          "assist": 0,
          "minute": ""
        },
        {
          "name": "Filippa Sjostrom",
          "goal": 0,
          "assist": 0,
          "minute": ""
        }
      ]
    },
    {
      "matchId": 13292707,
      "date": "2025-04-14",
      "opponent": "Hammarby IF",
      "homeAway": "Away",
      "result": "LOOSE",
      "teamScore": 0,
      "oppScore": 4,
      "league": "Damallsvenskan",
      "players": [
        {
          "name": "Eartha Cumings",
          "goal": 0,
          "assist": 0,
          "minute": ""
        },
        {
          "name": "Emilie Woldvik",
          "goal": 0,
          "assist": 0,
          "minute": ""
        },
        {
          "name": "Halimatu Ayinde",
          "goal": 0,
          "assist": 0,
          "minute": ""
        },
        {
          "name": "Guðrún Arnardóttir",
          "goal": 0,
          "assist": 0,
          "minute": ""
        },
        {
          "name": "Jo-Anne Cronquist",
          "goal": 0,
          "assist": 0,
          "minute": ""
        },
        {
          "name": "Anni Hartikainen",
          "goal": 0,
          "assist": 0,
          "minute": ""
        },
        {
          "name": "Emilia Larsson",
          "goal": 0,
          "assist": 0,
          "minute": ""
        },
        {
          "name": "Emma Jansson",
          "goal": 0,
          "assist": 0,
          "minute": ""
        },
        {
          "name": "Emilia Pelgander",
          "goal": 0,
          "assist": 0,
          "minute": ""
        },
        {
          "name": "Bea Sprung",
          "goal": 0,
          "assist": 0,
          "minute": ""
        },
        {
          "name": "Oona Sevenius",
          "goal": 0,
          "assist": 0,
          "minute": ""
        },
        {
          "name": "Molly Johansson",
          "goal": 0,
          "assist": 0,
          "minute": ""
        },
        {
          "name": "Hanna Andersson",
          "goal": 0,
          "assist": 0,
          "minute": ""
        },
        {
          "name": "Emma Pennsater",
          "goal": 0,
          "assist": 0,
          "minute": ""
        },
        {
          "name": "Maja Johansson",
          "goal": 0,
          "assist": 0,
          "minute": ""
        },
        {
          "name": "Ísabella Tryggvadóttir",
          "goal": 0,
          "assist": 0,
          "minute": ""
        },
        {
          "name": "Saga Andersson",
          "goal": 0,
          "assist": 0,
          "minute": ""
        },
        {
          "name": "Angel Mukasa",
          "goal": 0,
          "assist": 0,
          "minute": ""
        },
        {
          "name": "Mikaela Stojanovska",
          "goal": 0,
          "assist": 0,
          "minute": ""
        },
        {
          "name": "Yuna Hazekawa",
          "goal": 0,
          "assist": 0,
          "minute": ""
        }
      ]
    },
    {
      "matchId": 13292704,
      "date": "2025-03-29",
      "opponent": "Växjö DFF",
      "homeAway": "Away",
      "result": "WIN",
      "teamScore": 1,
      "oppScore": 0,
      "league": "Damallsvenskan",
      "players": [
        {
          "name": "Eartha Cumings",
          "goal": 0,
          "assist": 0,
          "minute": ""
        },
        {
          "name": "Emilie Woldvik",
          "goal": 1,
          "assist": 0,
          "minute": 44,
          "goalType": "regular"
        },
        {
          "name": "Emma Pennsater",
          "goal": 0,
          "assist": 0,
          "minute": ""
        },
        {
          "name": "Guðrún Arnardóttir",
          "goal": 0,
          "assist": 0,
          "minute": ""
        },
        {
          "name": "Jo-Anne Cronquist",
          "goal": 0,
          "assist": 0,
          "minute": ""
        },
        {
          "name": "Molly Johansson",
          "goal": 0,
          "assist": 0,
          "minute": ""
        },
        {
          "name": "Emilia Larsson",
          "goal": 0,
          "assist": 0,
          "minute": ""
        },
        {
          "name": "Emma Jansson",
          "goal": 0,
          "assist": 0,
          "minute": ""
        },
        {
          "name": "Emilia Pelgander",
          "goal": 0,
          "assist": 0,
          "minute": ""
        },
        {
          "name": "Hanna Andersson",
          "goal": 0,
          "assist": 1,
          "minute": 44
        },
        {
          "name": "Oona Sevenius",
          "goal": 0,
          "assist": 0,
          "minute": ""
        },
        {
          "name": "Bea Sprung",
          "goal": 0,
          "assist": 0,
          "minute": ""
        },
        {
          "name": "Anni Hartikainen",
          "goal": 0,
          "assist": 0,
          "minute": ""
        },
        {
          "name": "Saga Andersson",
          "goal": 0,
          "assist": 0,
          "minute": ""
        },
        {
          "name": "Angel Mukasa",
          "goal": 0,
          "assist": 0,
          "minute": ""
        },
        {
          "name": "Mikaela Stojanovska",
          "goal": 0,
          "assist": 0,
          "minute": ""
        },
        {
          "name": "Halimatu Ayinde",
          "goal": 0,
          "assist": 0,
          "minute": ""
        },
        {
          "name": "Maja Johansson",
          "goal": 0,
          "assist": 0,
          "minute": ""
        },
        {
          "name": "Ísabella Tryggvadóttir",
          "goal": 0,
          "assist": 0,
          "minute": ""
        }
      ]
    },
    {
      "matchId": 13292694,
      "date": "2025-03-23",
      "opponent": "Piteå IF",
      "homeAway": "Home",
      "result": "WIN",
      "teamScore": 1,
      "oppScore": 0,
      "league": "Damallsvenskan",
      "players": [
        {
          "name": "Eartha Cumings",
          "goal": 0,
          "assist": 0,
          "minute": ""
        },
        {
          "name": "Emilie Woldvik",
          "goal": 0,
          "assist": 1,
          "minute": 46
        },
        {
          "name": "Emma Pennsater",
          "goal": 0,
          "assist": 0,
          "minute": ""
        },
        {
          "name": "Halimatu Ayinde",
          "goal": 0,
          "assist": 0,
          "minute": ""
        },
        {
          "name": "Jo-Anne Cronquist",
          "goal": 0,
          "assist": 0,
          "minute": ""
        },
        {
          "name": "Emma Jansson",
          "goal": 0,
          "assist": 0,
          "minute": ""
        },
        {
          "name": "Emilia Pelgander",
          "goal": 0,
          "assist": 0,
          "minute": ""
        },
        {
          "name": "Molly Johansson",
          "goal": 0,
          "assist": 0,
          "minute": ""
        },
        {
          "name": "Bea Sprung",
          "goal": 0,
          "assist": 0,
          "minute": ""
        },
        {
          "name": "Oona Sevenius",
          "goal": 1,
          "assist": 0,
          "minute": 46,
          "goalType": "regular"
        },
        {
          "name": "Hanna Andersson",
          "goal": 0,
          "assist": 0,
          "minute": ""
        },
        {
          "name": "Anni Hartikainen",
          "goal": 0,
          "assist": 0,
          "minute": ""
        },
        {
          "name": "Guðrún Arnardóttir",
          "goal": 0,
          "assist": 0,
          "minute": ""
        },
        {
          "name": "Emilia Larsson",
          "goal": 0,
          "assist": 0,
          "minute": ""
        },
        {
          "name": "Angel Mukasa",
          "goal": 0,
          "assist": 0,
          "minute": ""
        },
        {
          "name": "Saga Andersson",
          "goal": 0,
          "assist": 0,
          "minute": ""
        },
        {
          "name": "Mikaela Stojanovska",
          "goal": 0,
          "assist": 0,
          "minute": ""
        },
        {
          "name": "Alice Enehov",
          "goal": 0,
          "assist": 0,
          "minute": ""
        },
        {
          "name": "Maja Johansson",
          "goal": 0,
          "assist": 0,
          "minute": ""
        },
        {
          "name": "Anna Lovisa Yng",
          "goal": 0,
          "assist": 0,
          "minute": ""
        }
      ]
    },
    {
      "matchId": 13282903,
      "date": "2025-03-17",
      "opponent": "Växjö DFF",
      "homeAway": "Home",
      "result": "WIN",
      "teamScore": 2,
      "oppScore": 1,
      "league": "Svenska Cupen, Women, Group 1",
      "players": []
    },
    {
      "matchId": 13282887,
      "date": "2025-03-08",
      "opponent": "Malmo FF",
      "homeAway": "Away",
      "result": "DRAW",
      "teamScore": 1,
      "oppScore": 1,
      "league": "Svenska Cupen, Women, Group 1",
      "players": []
    },
    {
      "matchId": 13282886,
      "date": "2025-03-04",
      "opponent": "Linköpings FC",
      "homeAway": "Home",
      "result": "WIN",
      "teamScore": 2,
      "oppScore": 0,
      "league": "Svenska Cupen, Women, Group 1",
      "players": []
    },
    {
      "matchId": 13415670,
      "date": "2025-02-01",
      "opponent": "FC Nordsjælland",
      "homeAway": "Home",
      "result": "LOOSE",
      "teamScore": 0,
      "oppScore": 1,
      "league": "Women Club Friendly Games",
      "players": []
    },
    {
      "matchId": 13388397,
      "date": "2025-01-25",
      "opponent": "Brøndby IF",
      "homeAway": "Away",
      "result": "LOOSE",
      "teamScore": 0,
      "oppScore": 2,
      "league": "Women Club Friendly Games",
      "players": []
    },
    {
      "matchId": 11922122,
      "date": "2024-11-09",
      "opponent": "Djurgårdens IF DFF",
      "homeAway": "Away",
      "result": "WIN",
      "teamScore": 3,
      "oppScore": 0,
      "league": "Damallsvenskan",
      "players": [
        {
          "name": "Eartha Cumings",
          "goal": 0,
          "assist": 0,
          "minute": ""
        },
        {
          "name": "Ria Öling",
          "goal": 0,
          "assist": 0,
          "minute": ""
        },
        {
          "name": "Guðrún Arnardóttir",
          "goal": 0,
          "assist": 0,
          "minute": ""
        },
        {
          "name": "Rebecca Knaak",
          "goal": 0,
          "assist": 0,
          "minute": ""
        },
        {
          "name": "Anni Hartikainen",
          "goal": 0,
          "assist": 0,
          "minute": ""
        },
        {
          "name": "Hanna Andersson",
          "goal": 0,
          "assist": 0,
          "minute": ""
        },
        {
          "name": "Caroline Seger",
          "goal": 0,
          "assist": 0,
          "minute": ""
        },
        {
          "name": "Momoko Tanikawa",
          "goal": 1,
          "assist": 0,
          "minute": 27,
          "goalType": "regular"
        },
        {
          "name": "Olivia Schough",
          "goal": 1,
          "assist": 0,
          "minute": 50,
          "goalType": "regular"
        },
        {
          "name": "Bea Sprung",
          "goal": 1,
          "assist": 0,
          "minute": 56,
          "goalType": "regular"
        },
        {
          "name": "Mai Kadowaki",
          "goal": 0,
          "assist": 1,
          "minute": 56
        },
        {
          "name": "Jessica Wik",
          "goal": 0,
          "assist": 0,
          "minute": ""
        },
        {
          "name": "Jo-Anne Cronquist",
          "goal": 0,
          "assist": 0,
          "minute": ""
        },
        {
          "name": "Emilia Larsson",
          "goal": 0,
          "assist": 0,
          "minute": ""
        },
        {
          "name": "Mikaela Stojanovska",
          "goal": 0,
          "assist": 0,
          "minute": ""
        },
        {
          "name": "Emma Berglund",
          "goal": 0,
          "assist": 0,
          "minute": ""
        },
        {
          "name": "Shannon Lynn",
          "goal": 0,
          "assist": 0,
          "minute": ""
        },
        {
          "name": "Emma Jansson",
          "goal": 0,
          "assist": 0,
          "minute": ""
        }
      ]
    },
    {
      "matchId": 11922110,
      "date": "2024-11-03",
      "opponent": "Linköpings FC",
      "homeAway": "Home",
      "result": "WIN",
      "teamScore": 4,
      "oppScore": 0,
      "league": "Damallsvenskan",
      "players": [
        {
          "name": "Eartha Cumings",
          "goal": 0,
          "assist": 0,
          "minute": ""
        },
        {
          "name": "Emma Jansson",
          "goal": 0,
          "assist": 0,
          "minute": ""
        },
        {
          "name": "Guðrún Arnardóttir",
          "goal": 0,
          "assist": 0,
          "minute": ""
        },
        {
          "name": "Rebecca Knaak",
          "goal": 1,
          "assist": 0,
          "minute": 79,
          "goalType": "regular"
        },
        {
          "name": "Jessica Wik",
          "goal": 0,
          "assist": 0,
          "minute": ""
        },
        {
          "name": "Caroline Seger",
          "goal": 0,
          "assist": 0,
          "minute": ""
        },
        {
          "name": "Momoko Tanikawa",
          "goal": 1,
          "assist": 0,
          "minute": 87,
          "goalType": "regular"
        },
        {
          "name": "Ria Öling",
          "goal": 0,
          "assist": 0,
          "minute": ""
        },
        {
          "name": "Bea Sprung",
          "goal": 0,
          "assist": 1,
          "minute": 79
        },
        {
          "name": "Mai Kadowaki",
          "goal": 0,
          "assist": 0,
          "minute": ""
        },
        {
          "name": "Olivia Schough",
          "goal": 1,
          "assist": 0,
          "minute": 36,
          "goalType": "penalty"
        },
        {
          "name": "Anni Hartikainen",
          "goal": 0,
          "assist": 0,
          "minute": ""
        },
        {
          "name": "Hanna Andersson",
          "goal": 0,
          "assist": 0,
          "minute": ""
        },
        {
          "name": "Jo-Anne Cronquist",
          "goal": 0,
          "assist": 0,
          "minute": ""
        },
        {
          "name": "Mikaela Stojanovska",
          "goal": 0,
          "assist": 0,
          "minute": ""
        },
        {
          "name": "Filippa Sjostrom",
          "goal": 0,
          "assist": 0,
          "minute": ""
        },
        {
          "name": "Shannon Lynn",
          "goal": 0,
          "assist": 0,
          "minute": ""
        },
        {
          "name": "Emilia Larsson",
          "goal": 0,
          "assist": 0,
          "minute": ""
        }
      ]
    },
    {
      "matchId": 11922103,
      "date": "2024-10-20",
      "opponent": "Hammarby IF",
      "homeAway": "Home",
      "result": "LOOSE",
      "teamScore": 2,
      "oppScore": 3,
      "league": "Damallsvenskan",
      "players": [
        {
          "name": "Eartha Cumings",
          "goal": 0,
          "assist": 0,
          "minute": ""
        },
        {
          "name": "Anni Hartikainen",
          "goal": 0,
          "assist": 0,
          "minute": ""
        },
        {
          "name": "Emma Jansson",
          "goal": 0,
          "assist": 0,
          "minute": ""
        },
        {
          "name": "Guðrún Arnardóttir",
          "goal": 0,
          "assist": 0,
          "minute": ""
        },
        {
          "name": "Rebecca Knaak",
          "goal": 0,
          "assist": 0,
          "minute": ""
        },
        {
          "name": "Jessica Wik",
          "goal": 0,
          "assist": 0,
          "minute": ""
        },
        {
          "name": "Emilia Larsson",
          "goal": 0,
          "assist": 0,
          "minute": ""
        },
        {
          "name": "Ria Öling",
          "goal": 0,
          "assist": 0,
          "minute": ""
        },
        {
          "name": "Momoko Tanikawa",
          "goal": 0,
          "assist": 0,
          "minute": ""
        },
        {
          "name": "Olivia Schough",
          "goal": 1,
          "assist": 0,
          "minute": 26,
          "goalType": "regular"
        },
        {
          "name": "Mai Kadowaki",
          "goal": 1,
          "assist": 1,
          "minute": 26
        },
        {
          "name": "Bea Sprung",
          "goal": 0,
          "assist": 0,
          "minute": ""
        },
        {
          "name": "Shannon Lynn",
          "goal": 0,
          "assist": 0,
          "minute": ""
        },
        {
          "name": "Jo-Anne Cronquist",
          "goal": 0,
          "assist": 0,
          "minute": ""
        },
        {
          "name": "Mikaela Stojanovska",
          "goal": 0,
          "assist": 0,
          "minute": ""
        },
        {
          "name": "Hanna Andersson",
          "goal": 0,
          "assist": 0,
          "minute": ""
        },
        {
          "name": "Alice Enehov",
          "goal": 0,
          "assist": 0,
          "minute": ""
        },
        {
          "name": "Filippa Sjostrom",
          "goal": 0,
          "assist": 0,
          "minute": ""
        }
      ]
    },
    {
      "matchId": 12851467,
      "date": "2024-10-16",
      "opponent": "Helsingborgs IF",
      "homeAway": "Away",
      "result": "WIN",
      "teamScore": 4,
      "oppScore": 0,
      "league": "Svenska Cupen, Women, Qualification",
      "players": []
    },
    {
      "matchId": 11922099,
      "date": "2024-10-12",
      "opponent": "Norrköping DFK",
      "homeAway": "Away",
      "result": "WIN",
      "teamScore": 1,
      "oppScore": 0,
      "league": "Damallsvenskan",
      "players": [
        {
          "name": "Eartha Cumings",
          "goal": 0,
          "assist": 0,
          "minute": ""
        },
        {
          "name": "Anni Hartikainen",
          "goal": 0,
          "assist": 0,
          "minute": ""
        },
        {
          "name": "Emma Jansson",
          "goal": 0,
          "assist": 0,
          "minute": ""
        },
        {
          "name": "Guðrún Arnardóttir",
          "goal": 0,
          "assist": 0,
          "minute": ""
        },
        {
          "name": "Rebecca Knaak",
          "goal": 0,
          "assist": 0,
          "minute": ""
        },
        {
          "name": "Emilia Larsson",
          "goal": 0,
          "assist": 0,
          "minute": ""
        },
        {
          "name": "Ria Öling",
          "goal": 0,
          "assist": 0,
          "minute": ""
        },
        {
          "name": "Momoko Tanikawa",
          "goal": 1,
          "assist": 0,
          "minute": 53,
          "goalType": "regular"
        },
        {
          "name": "Jessica Wik",
          "goal": 0,
          "assist": 0,
          "minute": ""
        },
        {
          "name": "Mai Kadowaki",
          "goal": 0,
          "assist": 1,
          "minute": 53
        },
        {
          "name": "Olivia Schough",
          "goal": 0,
          "assist": 0,
          "minute": ""
        },
        {
          "name": "Bea Sprung",
          "goal": 0,
          "assist": 0,
          "minute": ""
        },
        {
          "name": "Hanna Andersson",
          "goal": 0,
          "assist": 0,
          "minute": ""
        },
        {
          "name": "Disa Hellwig",
          "goal": 0,
          "assist": 0,
          "minute": ""
        },
        {
          "name": "Jo-Anne Cronquist",
          "goal": 0,
          "assist": 0,
          "minute": ""
        },
        {
          "name": "Mikaela Stojanovska",
          "goal": 0,
          "assist": 0,
          "minute": ""
        },
        {
          "name": "Rebecca Maravall Almqvist",
          "goal": 0,
          "assist": 0,
          "minute": ""
        }
      ]
    },
    {
      "matchId": 11922088,
      "date": "2024-10-04",
      "opponent": "Kristianstads DFF",
      "homeAway": "Home",
      "result": "WIN",
      "teamScore": 2,
      "oppScore": 1,
      "league": "Damallsvenskan",
      "players": [
        {
          "name": "Eartha Cumings",
          "goal": 0,
          "assist": 0,
          "minute": ""
        },
        {
          "name": "Emma Jansson",
          "goal": 0,
          "assist": 0,
          "minute": ""
        },
        {
          "name": "Guðrún Arnardóttir",
          "goal": 0,
          "assist": 1,
          "minute": 20
        },
        {
          "name": "Rebecca Knaak",
          "goal": 2,
          "assist": 0,
          "minute": 77,
          "goalType": "regular"
        },
        {
          "name": "Ria Öling",
          "goal": 0,
          "assist": 0,
          "minute": ""
        },
        {
          "name": "Jessica Wik",
          "goal": 0,
          "assist": 0,
          "minute": ""
        },
        {
          "name": "Caroline Seger",
          "goal": 0,
          "assist": 0,
          "minute": ""
        },
        {
          "name": "Momoko Tanikawa",
          "goal": 0,
          "assist": 1,
          "minute": 77
        },
        {
          "name": "Olivia Schough",
          "goal": 0,
          "assist": 0,
          "minute": ""
        },
        {
          "name": "Emilia Larsson",
          "goal": 0,
          "assist": 0,
          "minute": ""
        },
        {
          "name": "Mai Kadowaki",
          "goal": 0,
          "assist": 0,
          "minute": ""
        },
        {
          "name": "Anni Hartikainen",
          "goal": 0,
          "assist": 0,
          "minute": ""
        },
        {
          "name": "Shannon Lynn",
          "goal": 0,
          "assist": 0,
          "minute": ""
        },
        {
          "name": "Jo-Anne Cronquist",
          "goal": 0,
          "assist": 0,
          "minute": ""
        },
        {
          "name": "Mikaela Stojanovska",
          "goal": 0,
          "assist": 0,
          "minute": ""
        },
        {
          "name": "Bea Sprung",
          "goal": 0,
          "assist": 0,
          "minute": ""
        },
        {
          "name": "Hanna Andersson",
          "goal": 0,
          "assist": 0,
          "minute": ""
        },
        {
          "name": "Rebecca Maravall Almqvist",
          "goal": 0,
          "assist": 0,
          "minute": ""
        }
      ]
    },
    {
      "matchId": 11922087,
      "date": "2024-09-30",
      "opponent": "Piteå IF",
      "homeAway": "Away",
      "result": "WIN",
      "teamScore": 1,
      "oppScore": 0,
      "league": "Damallsvenskan",
      "players": [
        {
          "name": "Eartha Cumings",
          "goal": 0,
          "assist": 0,
          "minute": ""
        },
        {
          "name": "Emma Jansson",
          "goal": 0,
          "assist": 0,
          "minute": ""
        },
        {
          "name": "Guðrún Arnardóttir",
          "goal": 0,
          "assist": 0,
          "minute": ""
        },
        {
          "name": "Rebecca Knaak",
          "goal": 0,
          "assist": 0,
          "minute": ""
        },
        {
          "name": "Anni Hartikainen",
          "goal": 0,
          "assist": 0,
          "minute": ""
        },
        {
          "name": "Caroline Seger",
          "goal": 0,
          "assist": 0,
          "minute": ""
        },
        {
          "name": "Momoko Tanikawa",
          "goal": 1,
          "assist": 0,
          "minute": 29,
          "goalType": "regular"
        },
        {
          "name": "Ria Öling",
          "goal": 0,
          "assist": 0,
          "minute": ""
        },
        {
          "name": "Emilia Larsson",
          "goal": 0,
          "assist": 0,
          "minute": ""
        },
        {
          "name": "Mai Kadowaki",
          "goal": 0,
          "assist": 0,
          "minute": ""
        },
        {
          "name": "Olivia Schough",
          "goal": 0,
          "assist": 0,
          "minute": ""
        },
        {
          "name": "Jessica Wik",
          "goal": 0,
          "assist": 0,
          "minute": ""
        },
        {
          "name": "Hanna Andersson",
          "goal": 0,
          "assist": 0,
          "minute": ""
        },
        {
          "name": "Shannon Lynn",
          "goal": 0,
          "assist": 0,
          "minute": ""
        },
        {
          "name": "Jo-Anne Cronquist",
          "goal": 0,
          "assist": 0,
          "minute": ""
        },
        {
          "name": "Mikaela Stojanovska",
          "goal": 0,
          "assist": 0,
          "minute": ""
        },
        {
          "name": "Bea Sprung",
          "goal": 0,
          "assist": 0,
          "minute": ""
        },
        {
          "name": "Rebecca Maravall Almqvist",
          "goal": 0,
          "assist": 0,
          "minute": ""
        }
      ]
    },
    {
      "matchId": 11922074,
      "date": "2024-09-19",
      "opponent": "Växjö DFF",
      "homeAway": "Home",
      "result": "WIN",
      "teamScore": 4,
      "oppScore": 0,
      "league": "Damallsvenskan",
      "players": [
        {
          "name": "Eartha Cumings",
          "goal": 0,
          "assist": 0,
          "minute": ""
        },
        {
          "name": "Ria Öling",
          "goal": 0,
          "assist": 0,
          "minute": ""
        },
        {
          "name": "Emma Jansson",
          "goal": 1,
          "assist": 0,
          "minute": 42,
          "goalType": "regular"
        },
        {
          "name": "Guðrún Arnardóttir",
          "goal": 0,
          "assist": 0,
          "minute": ""
        },
        {
          "name": "Rebecca Knaak",
          "goal": 0,
          "assist": 0,
          "minute": ""
        },
        {
          "name": "Bea Sprung",
          "goal": 0,
          "assist": 0,
          "minute": ""
        },
        {
          "name": "Caroline Seger",
          "goal": 0,
          "assist": 0,
          "minute": ""
        },
        {
          "name": "Momoko Tanikawa",
          "goal": 0,
          "assist": 1,
          "minute": 42
        },
        {
          "name": "Olivia Schough",
          "goal": 1,
          "assist": 0,
          "minute": 24,
          "goalType": "regular"
        },
        {
          "name": "Mai Kadowaki",
          "goal": 2,
          "assist": 0,
          "minute": 80,
          "goalType": "regular"
        },
        {
          "name": "Hanna Andersson",
          "goal": 0,
          "assist": 0,
          "minute": ""
        },
        {
          "name": "Anni Hartikainen",
          "goal": 0,
          "assist": 0,
          "minute": ""
        },
        {
          "name": "Jo-Anne Cronquist",
          "goal": 0,
          "assist": 0,
          "minute": ""
        },
        {
          "name": "Mikaela Stojanovska",
          "goal": 0,
          "assist": 0,
          "minute": ""
        },
        {
          "name": "Rebecca Maravall Almqvist",
          "goal": 0,
          "assist": 0,
          "minute": ""
        },
        {
          "name": "Alice Enehov",
          "goal": 0,
          "assist": 0,
          "minute": ""
        },
        {
          "name": "Shannon Lynn",
          "goal": 0,
          "assist": 0,
          "minute": ""
        },
        {
          "name": "Disa Hellwig",
          "goal": 0,
          "assist": 0,
          "minute": ""
        }
      ]
    },
    {
      "matchId": 11922070,
      "date": "2024-09-14",
      "opponent": "KIF Örebro DFF",
      "homeAway": "Away",
      "result": "WIN",
      "teamScore": 4,
      "oppScore": 0,
      "league": "Damallsvenskan",
      "players": [
        {
          "name": "Eartha Cumings",
          "goal": 0,
          "assist": 0,
          "minute": ""
        },
        {
          "name": "Ria Öling",
          "goal": 0,
          "assist": 0,
          "minute": ""
        },
        {
          "name": "Emma Jansson",
          "goal": 0,
          "assist": 0,
          "minute": ""
        },
        {
          "name": "Guðrún Arnardóttir",
          "goal": 0,
          "assist": 0,
          "minute": ""
        },
        {
          "name": "Rebecca Knaak",
          "goal": 0,
          "assist": 1,
          "minute": 41
        },
        {
          "name": "Emilia Larsson",
          "goal": 2,
          "assist": 0,
          "minute": 90,
          "goalType": "regular"
        },
        {
          "name": "Caroline Seger",
          "goal": 0,
          "assist": 0,
          "minute": ""
        },
        {
          "name": "Momoko Tanikawa",
          "goal": 1,
          "assist": 0,
          "minute": 15,
          "goalType": "regular"
        },
        {
          "name": "Olivia Schough",
          "goal": 0,
          "assist": 0,
          "minute": ""
        },
        {
          "name": "Olivia Holdt",
          "goal": 0,
          "assist": 0,
          "minute": ""
        },
        {
          "name": "Mai Kadowaki",
          "goal": 1,
          "assist": 0,
          "minute": 41,
          "goalType": "regular"
        },
        {
          "name": "Bea Sprung",
          "goal": 0,
          "assist": 0,
          "minute": ""
        },
        {
          "name": "Hanna Andersson",
          "goal": 0,
          "assist": 1,
          "minute": 72
        },
        {
          "name": "Jo-Anne Cronquist",
          "goal": 0,
          "assist": 0,
          "minute": ""
        },
        {
          "name": "Mikaela Stojanovska",
          "goal": 0,
          "assist": 0,
          "minute": ""
        },
        {
          "name": "Rebecca Maravall Almqvist",
          "goal": 0,
          "assist": 1,
          "minute": 90
        },
        {
          "name": "Shannon Lynn",
          "goal": 0,
          "assist": 0,
          "minute": ""
        },
        {
          "name": "Alice Enehov",
          "goal": 0,
          "assist": 0,
          "minute": ""
        }
      ]
    },
    {
      "matchId": 11922059,
      "date": "2024-09-06",
      "opponent": "IF Brommapojkarna",
      "homeAway": "Home",
      "result": "WIN",
      "teamScore": 3,
      "oppScore": 0,
      "league": "Damallsvenskan",
      "players": [
        {
          "name": "Eartha Cumings",
          "goal": 0,
          "assist": 0,
          "minute": ""
        },
        {
          "name": "Anni Hartikainen",
          "goal": 0,
          "assist": 0,
          "minute": ""
        },
        {
          "name": "Emma Jansson",
          "goal": 0,
          "assist": 0,
          "minute": ""
        },
        {
          "name": "Guðrún Arnardóttir",
          "goal": 0,
          "assist": 0,
          "minute": ""
        },
        {
          "name": "Rebecca Knaak",
          "goal": 0,
          "assist": 0,
          "minute": ""
        },
        {
          "name": "Olivia Schough",
          "goal": 0,
          "assist": 1,
          "minute": 18
        },
        {
          "name": "Momoko Tanikawa",
          "goal": 0,
          "assist": 0,
          "minute": ""
        },
        {
          "name": "Ria Öling",
          "goal": 0,
          "assist": 1,
          "minute": 45
        },
        {
          "name": "Caroline Seger",
          "goal": 0,
          "assist": 0,
          "minute": ""
        },
        {
          "name": "Olivia Holdt",
          "goal": 1,
          "assist": 0,
          "minute": 45,
          "goalType": "regular"
        },
        {
          "name": "Mai Kadowaki",
          "goal": 1,
          "assist": 0,
          "minute": 18,
          "goalType": "regular"
        },
        {
          "name": "Emilia Larsson",
          "goal": 1,
          "assist": 0,
          "minute": 83,
          "goalType": "regular"
        },
        {
          "name": "Hanna Andersson",
          "goal": 0,
          "assist": 0,
          "minute": ""
        },
        {
          "name": "Jo-Anne Cronquist",
          "goal": 0,
          "assist": 0,
          "minute": ""
        },
        {
          "name": "Mikaela Stojanovska",
          "goal": 0,
          "assist": 0,
          "minute": ""
        },
        {
          "name": "Bea Sprung",
          "goal": 0,
          "assist": 0,
          "minute": ""
        },
        {
          "name": "Shannon Lynn",
          "goal": 0,
          "assist": 0,
          "minute": ""
        },
        {
          "name": "Filippa Sjostrom",
          "goal": 0,
          "assist": 0,
          "minute": ""
        }
      ]
    },
    {
      "matchId": 11922057,
      "date": "2024-08-31",
      "opponent": "AIK",
      "homeAway": "Away",
      "result": "WIN",
      "teamScore": 5,
      "oppScore": 1,
      "league": "Damallsvenskan",
      "players": [
        {
          "name": "Eartha Cumings",
          "goal": 0,
          "assist": 0,
          "minute": ""
        },
        {
          "name": "Jessica Wik",
          "goal": 0,
          "assist": 0,
          "minute": ""
        },
        {
          "name": "Anni Hartikainen",
          "goal": 0,
          "assist": 0,
          "minute": ""
        },
        {
          "name": "Guðrún Arnardóttir",
          "goal": 0,
          "assist": 0,
          "minute": ""
        },
        {
          "name": "Rebecca Knaak",
          "goal": 1,
          "assist": 0,
          "minute": 13,
          "goalType": "regular"
        },
        {
          "name": "Caroline Seger",
          "goal": 0,
          "assist": 0,
          "minute": ""
        },
        {
          "name": "Ria Öling",
          "goal": 0,
          "assist": 0,
          "minute": ""
        },
        {
          "name": "Momoko Tanikawa",
          "goal": 1,
          "assist": 2,
          "minute": 57,
          "goalType": "regular"
        },
        {
          "name": "Emilia Larsson",
          "goal": 0,
          "assist": 0,
          "minute": ""
        },
        {
          "name": "Mai Kadowaki",
          "goal": 2,
          "assist": 1,
          "minute": 57
        },
        {
          "name": "Olivia Schough",
          "goal": 0,
          "assist": 0,
          "minute": ""
        },
        {
          "name": "Bea Sprung",
          "goal": 0,
          "assist": 0,
          "minute": ""
        },
        {
          "name": "Emma Jansson",
          "goal": 0,
          "assist": 0,
          "minute": ""
        },
        {
          "name": "Jo-Anne Cronquist",
          "goal": 0,
          "assist": 0,
          "minute": ""
        },
        {
          "name": "Olivia Holdt",
          "goal": 0,
          "assist": 0,
          "minute": ""
        },
        {
          "name": "Hanna Andersson",
          "goal": 0,
          "assist": 0,
          "minute": ""
        },
        {
          "name": "Shannon Lynn",
          "goal": 0,
          "assist": 0,
          "minute": ""
        },
        {
          "name": "Mikaela Stojanovska",
          "goal": 0,
          "assist": 0,
          "minute": ""
        }
      ]
    },
    {
      "matchId": 11922045,
      "date": "2024-08-26",
      "opponent": "BK Häcken FF",
      "homeAway": "Home",
      "result": "WIN",
      "teamScore": 1,
      "oppScore": 0,
      "league": "Damallsvenskan",
      "players": [
        {
          "name": "Eartha Cumings",
          "goal": 0,
          "assist": 0,
          "minute": ""
        },
        {
          "name": "Jessica Wik",
          "goal": 0,
          "assist": 0,
          "minute": ""
        },
        {
          "name": "Guðrún Arnardóttir",
          "goal": 1,
          "assist": 0,
          "minute": 66,
          "goalType": "regular"
        },
        {
          "name": "Rebecca Knaak",
          "goal": 0,
          "assist": 1,
          "minute": 66
        },
        {
          "name": "Anni Hartikainen",
          "goal": 0,
          "assist": 0,
          "minute": ""
        },
        {
          "name": "Caroline Seger",
          "goal": 0,
          "assist": 0,
          "minute": ""
        },
        {
          "name": "Momoko Tanikawa",
          "goal": 0,
          "assist": 0,
          "minute": ""
        },
        {
          "name": "Ria Öling",
          "goal": 0,
          "assist": 0,
          "minute": ""
        },
        {
          "name": "Olivia Schough",
          "goal": 0,
          "assist": 0,
          "minute": ""
        },
        {
          "name": "Mai Kadowaki",
          "goal": 0,
          "assist": 0,
          "minute": ""
        },
        {
          "name": "Emilia Larsson",
          "goal": 0,
          "assist": 0,
          "minute": ""
        },
        {
          "name": "Hanna Andersson",
          "goal": 0,
          "assist": 0,
          "minute": ""
        },
        {
          "name": "Shannon Lynn",
          "goal": 0,
          "assist": 0,
          "minute": ""
        },
        {
          "name": "Emma Jansson",
          "goal": 0,
          "assist": 0,
          "minute": ""
        },
        {
          "name": "Jo-Anne Cronquist",
          "goal": 0,
          "assist": 0,
          "minute": ""
        },
        {
          "name": "Mikaela Stojanovska",
          "goal": 0,
          "assist": 0,
          "minute": ""
        },
        {
          "name": "Bea Sprung",
          "goal": 0,
          "assist": 0,
          "minute": ""
        },
        {
          "name": "Rebecca Maravall Almqvist",
          "goal": 0,
          "assist": 0,
          "minute": ""
        }
      ]
    }
  ]
}